{
  "name": "Meetings",
  "version": "0.1.1",
  "runtime": "vite_hono",
  "visibility": "public",
  "description": "Record, transcribe, and summarize meetings with real-time transcription",
  "author": "Moldable Team",
  "license": "MIT",
  "repository": "moldable-ai/apps",
  "icon": "🎙️",
  "iconPath": "public/icon.png",
  "widgetSize": "medium",
  "widgetTint": "violet",
  "category": "productivity",
  "tags": ["meetings", "transcription", "audio", "recording"],
  "moldableDependencies": {
    "@moldable-ai/ui": "^0.2.6",
    "@moldable-ai/editor": "^0.1.5",
    "@moldable-ai/storage": "^0.1.3"
  },
  "env": [],
  "vault": [
    {
      "key": "DEEPGRAM_API_KEY",
      "name": "Deepgram API Key",
      "description": "Powers real-time speech-to-text transcription",
      "url": "https://console.deepgram.com/",
      "required": true,
      "capabilities": ["deepgram/auth-grant"]
    }
  ],
  "upstream": {
    "repo": "moldable-ai/apps",
    "path": "meetings",
    "installedVersion": "0.1.0",
    "installedCommit": "79c470e37f19631020babbc35646d6ef4eb515fa",
    "installedAt": "2026-01-15T03:56:56Z"
  },
  "modified": false,
  "routeName": "meetings"
}
